maphub/__init__.py
maphub/cli.py
maphub/client.py
maphub/exceptions.py
maphub/endpoints/__init__.py
maphub/endpoints/base.py
maphub/endpoints/folder.py
maphub/endpoints/maps.py
maphub/endpoints/project.py
maphub/endpoints/versions.py
maphub/endpoints/workspace.py
maphub-0.2.14.dist-info/licenses/LICENSE
maphub-0.2.14.dist-info/METADATA
maphub-0.2.14.dist-info/WHEEL
maphub-0.2.14.dist-info/entry_points.txt
maphub-0.2.14.dist-info/top_level.txt
maphub-0.2.14.dist-info/RECORD
