Metadata-Version: 2.4
Name: maphub
Version: 0.2.14
Summary: A Python wrapper for the MapHub API
Author-email: MapHub <maphub@meteory.eu>
Project-URL: repository, https://github.com/maphub-co/maphub-python
Requires-Python: >=3.12
License-File: LICENSE
Requires-Dist: requests>=2.25.1
Provides-Extra: dev
Requires-Dist: pytest>=7.0; extra == "dev"
Requires-Dist: black>=22.0; extra == "dev"
Dynamic: license-file
